skyledge_sdk/__init__.py
skyledge_sdk/api_client.py
skyledge_sdk/api_response.py
skyledge_sdk/configuration.py
skyledge_sdk/exceptions.py
skyledge_sdk/py.typed
skyledge_sdk/rest.py
skyledge_sdk/api/__init__.py
skyledge_sdk/api/api_keys_api.py
skyledge_sdk/api/apps_api.py
skyledge_sdk/api/asset_types_api.py
skyledge_sdk/api/assets_api.py
skyledge_sdk/api/attachments_api.py
skyledge_sdk/api/billing_api.py
skyledge_sdk/api/collaborators_api.py
skyledge_sdk/api/control_rooms_api.py
skyledge_sdk/api/cycle_types_api.py
skyledge_sdk/api/cycles_api.py
skyledge_sdk/api/errors_api.py
skyledge_sdk/api/event_types_api.py
skyledge_sdk/api/events_api.py
skyledge_sdk/api/form_api.py
skyledge_sdk/api/forms_api.py
skyledge_sdk/api/organization_api.py
skyledge_sdk/api/place_types_api.py
skyledge_sdk/api/places_api.py
skyledge_sdk/api/rule_types_api.py
skyledge_sdk/api/rules_api.py
skyledge_sdk/api/task_types_api.py
skyledge_sdk/api/tasks_api.py
skyledge_sdk/api/users_api.py
skyledge_sdk/models/__init__.py
skyledge_sdk/models/action.py
skyledge_sdk/models/aggregated_response.py
skyledge_sdk/models/aggregation_parameter_request.py
skyledge_sdk/models/api_key_response.py
skyledge_sdk/models/api_keys_response.py
skyledge_sdk/models/asset_attachments.py
skyledge_sdk/models/asset_attachments_response.py
skyledge_sdk/models/asset_count.py
skyledge_sdk/models/asset_location_response.py
skyledge_sdk/models/asset_map_view_response.py
skyledge_sdk/models/asset_metric_response.py
skyledge_sdk/models/asset_request.py
skyledge_sdk/models/asset_response.py
skyledge_sdk/models/asset_search_request.py
skyledge_sdk/models/asset_snapshot_response.py
skyledge_sdk/models/asset_table_view_response.py
skyledge_sdk/models/asset_type_request.py
skyledge_sdk/models/asset_type_response.py
skyledge_sdk/models/asset_types.py
skyledge_sdk/models/assets.py
skyledge_sdk/models/assets_aggregation_response.py
skyledge_sdk/models/attachment_resource.py
skyledge_sdk/models/attachment_response.py
skyledge_sdk-1.0.17.dist-info/METADATA
skyledge_sdk-1.0.17.dist-info/WHEEL
skyledge_sdk-1.0.17.dist-info/top_level.txt
skyledge_sdk-1.0.17.dist-info/RECORD
